signal_client/__init__.py
signal_client/adapters/__init__.py
signal_client/adapters/api/__init__.py
signal_client/adapters/api/accounts_client.py
signal_client/adapters/api/attachments_client.py
signal_client/adapters/api/base_client.py
signal_client/adapters/api/contacts_client.py
signal_client/adapters/api/devices_client.py
signal_client/adapters/api/general_client.py
signal_client/adapters/api/groups_client.py
signal_client/adapters/api/identities_client.py
signal_client/adapters/api/messages_client.py
signal_client/adapters/api/profiles_client.py
signal_client/adapters/api/reactions_client.py
signal_client/adapters/api/receipts_client.py
signal_client/adapters/api/request_options.py
signal_client/adapters/api/schemas/__init__.py
signal_client/adapters/api/schemas/contact.py
signal_client/adapters/api/schemas/contacts.py
signal_client/adapters/api/schemas/events.py
signal_client/adapters/api/schemas/group.py
signal_client/adapters/api/schemas/groups.py
signal_client/adapters/api/schemas/link_preview.py
signal_client/adapters/api/schemas/message.py
signal_client/adapters/api/schemas/messages.py
signal_client/adapters/api/schemas/profiles.py
signal_client/adapters/api/schemas/quote.py
signal_client/adapters/api/schemas/reaction.py
signal_client/adapters/api/schemas/reactions.py
signal_client/adapters/api/schemas/receipts.py
signal_client/adapters/api/schemas/requests.py
signal_client/adapters/api/schemas/responses.py
signal_client/adapters/api/search_client.py
signal_client/adapters/api/sticker_packs_client.py
signal_client/adapters/storage/__init__.py
signal_client/adapters/storage/base.py
signal_client/adapters/storage/memory.py
signal_client/adapters/storage/redis.py
signal_client/adapters/storage/sqlite.py
signal_client/adapters/transport/__init__.py
signal_client/adapters/transport/websocket_client.py
signal_client/app/__init__.py
signal_client/app/application.py
signal_client/app/bot.py
signal_client/app/cli.py
signal_client/core/__init__.py
signal_client-0.1.6.dist-info/METADATA
signal_client-0.1.6.dist-info/WHEEL
signal_client-0.1.6.dist-info/entry_points.txt
signal_client-0.1.6.dist-info/licenses/LICENSE
signal_client-0.1.6.dist-info/RECORD
