Metadata-Version: 2.4
Name: signal_client
Version: 0.1.6
Summary: Async Python framework for resilient Signal bots. Build fast on `bbernhard/signal-cli-rest-api` with typed helpers, resilient ingestion, and observability baked in.
License: MIT
License-File: LICENSE
Keywords: Signal,Bot,Framework,Async,Python,Resilient,Observability,Messaging
Author: cornellsh
Requires-Python: >=3.10,<3.14
Classifier: Development Status :: 4 - Beta
Classifier: Framework :: AsyncIO
Classifier: Intended Audience :: Developers
Classifier: License :: OSI Approved :: MIT License
Classifier: Operating System :: OS Independent
Classifier: Programming Language :: Python :: 3
Classifier: Programming Language :: Python :: 3.10
Classifier: Programming Language :: Python :: 3.11
Classifier: Programming Language :: Python :: 3.12
Classifier: Programming Language :: Python :: 3.13
Classifier: Programming Language :: Python :: 3.9
Classifier: Topic :: Software Development :: Libraries :: Python Modules
Requires-Dist: APScheduler (>=3.11.0,<4.0.0)
Requires-Dist: aiohttp (>=3.11.9,<4.0.0)
Requires-Dist: aiosqlite (>=0.20.0,<1.0.0)
Requires-Dist: eval-type-backport (>=0.2.0) ; python_version < "3.10"
Requires-Dist: packaging (>=25.0,<26.0)
Requires-Dist: phonenumbers (>=8.13.54,<9.0)
Requires-Dist: prometheus-client (>=0.20.0,<1.0.0)
Requires-Dist: pydantic (>=2.12.0,<2.13.0)
Requires-Dist: pydantic-settings (>=2.11.0,<2.12.0)
Requires-Dist: structlog (>=24.4.0,<24.5.0)
Requires-Dist: websockets (>=14.1,<15.0)
Project-URL: Bug Tracker, https://github.com/cornellsh/signal_client/issues
Project-URL: Documentation, https://github.com/cornellsh/signal_client#readme
Project-URL: Repository, https://github.com/cornellsh/signal_client
